omg_cli/__init__.py
omg_cli/__main__.py
omg_cli/templates/__init__.py.j2
omg_cli/templates/__manifest__.py.j2
omg_cli/templates/ir.model.access.csv.j2
omg_cli/templates/model.py.j2
omg_cli/templates/view.xml.j2
omg_cli-0.1.7.dist-info/LICENSE
omg_cli-0.1.7.dist-info/METADATA
omg_cli-0.1.7.dist-info/WHEEL
omg_cli-0.1.7.dist-info/entry_points.txt
omg_cli-0.1.7.dist-info/top_level.txt
omg_cli-0.1.7.dist-info/RECORD
