Metadata-Version: 2.1
Name: omg-cli
Version: 0.1.7
Summary: A tool to automate Odoo module creation
Home-page: https://github.com/heyzeeshan/odoo-module-generator
Author: Mohammed Zeeshan Jagirdar
Author-email: mzjagirdar10@gmail.com
Classifier: Programming Language :: Python :: 3
Classifier: License :: OSI Approved :: MIT License
Classifier: Operating System :: OS Independent
Requires-Python: >=3.6
License-File: LICENSE
Requires-Dist: Jinja2
